{
  "methods": {
    "addTab(android.widget.TabHost.TabSpec)": {
      "isImplementation": true,
      "modifiers": [
        "protected"
      ],
      "params": [
        "tabSpec"
      ],
      "returnType": "void",
      "exceptions": [],
      "name": "addTab(android.widget.TabHost.TabSpec)"
    },
    "getCurrentTab()": {
      "isImplementation": true,
      "modifiers": [
        "protected"
      ],
      "params": [],
      "returnType": "int",
      "exceptions": [],
      "name": "getCurrentTab()"
    },
    "getCurrentTabSpec()": {
      "isImplementation": false,
      "modifiers": [
        "public"
      ],
      "params": [],
      "returnType": "android.widget.TabHost.TabSpec",
      "exceptions": [],
      "name": "getCurrentTabSpec()"
    },
    "getCurrentTabTag()": {
      "isImplementation": true,
      "modifiers": [
        "protected"
      ],
      "params": [],
      "returnType": "java.lang.String",
      "exceptions": [],
      "name": "getCurrentTabTag()"
    },
    "getCurrentView()": {
      "isImplementation": true,
      "modifiers": [
        "protected"
      ],
      "params": [],
      "returnType": "android.view.View",
      "exceptions": [],
      "name": "getCurrentView()"
    },
    "getSpecByTag(java.lang.String)": {
      "isImplementation": false,
      "modifiers": [
        "public"
      ],
      "params": [
        "tag"
      ],
      "returnType": "android.widget.TabHost.TabSpec",
      "exceptions": [],
      "name": "getSpecByTag(java.lang.String)"
    },
    "getTabWidget()": {
      "isImplementation": true,
      "modifiers": [
        "protected"
      ],
      "params": [],
      "returnType": "android.widget.TabWidget",
      "exceptions": [],
      "name": "getTabWidget()"
    },
    "newTabSpec(java.lang.String)": {
      "isImplementation": true,
      "modifiers": [
        "protected"
      ],
      "params": [
        "tag"
      ],
      "returnType": "android.widget.TabHost.TabSpec",
      "exceptions": [],
      "name": "newTabSpec(java.lang.String)"
    },
    "setCurrentTab(int)": {
      "isImplementation": true,
      "modifiers": [
        "protected"
      ],
      "params": [
        "index"
      ],
      "returnType": "void",
      "exceptions": [],
      "name": "setCurrentTab(int)"
    },
    "setCurrentTabByTag(java.lang.String)": {
      "isImplementation": true,
      "modifiers": [
        "protected"
      ],
      "params": [
        "tag"
      ],
      "returnType": "void",
      "exceptions": [],
      "name": "setCurrentTabByTag(java.lang.String)"
    },
    "setOnTabChangedListener(android.widget.TabHost.OnTabChangeListener)": {
      "isImplementation": true,
      "modifiers": [
        "protected"
      ],
      "params": [
        "listener"
      ],
      "returnType": "void",
      "exceptions": [],
      "name": "setOnTabChangedListener(android.widget.TabHost.OnTabChangeListener)"
    }
  },
  "imports": [
    "android.R",
    "android.app.Activity",
    "android.content.Context",
    "android.content.Intent",
    "android.graphics.drawable.Drawable",
    "android.view.View",
    "android.widget.TabHost",
    "android.widget.TabHost.TabSpec",
    "android.widget.TabWidget",
    "java.util.ArrayList",
    "java.util.List",
    "org.robolectric.annotation.Implementation",
    "org.robolectric.annotation.Implements",
    "org.robolectric.annotation.RealObject",
    "org.robolectric.shadow.api.Shadow",
    "org.robolectric.shadows.ShadowTabHost.ShadowTabSpec"
  ],
  "name": "org.robolectric.shadows.ShadowTabHost"
}